django_apscheduler/__init__.py
django_apscheduler/admin.py
django_apscheduler/apps.py
django_apscheduler/jobstores.py
django_apscheduler/models.py
django_apscheduler/util.py
django_apscheduler/migrations/0001_initial.py
django_apscheduler/migrations/0002_auto_20180412_0758.py
django_apscheduler/migrations/0003_auto_20200716_1632.py
django_apscheduler/migrations/0004_auto_20200717_1043.py
django_apscheduler/migrations/0005_migrate_name_to_id.py
django_apscheduler/migrations/0006_remove_djangojob_name.py
django_apscheduler/migrations/0007_auto_20200717_1404.py
django_apscheduler/migrations/0008_remove_djangojobexecution_started.py
django_apscheduler/migrations/0009_djangojobexecution_unique_job_executions.py
django_apscheduler/migrations/__init__.py
django_apscheduler-0.7.0.dist-info/AUTHORS
django_apscheduler-0.7.0.dist-info/LICENSE
django_apscheduler-0.7.0.dist-info/METADATA
django_apscheduler-0.7.0.dist-info/WHEEL
django_apscheduler-0.7.0.dist-info/top_level.txt
django_apscheduler-0.7.0.dist-info/RECORD
