Metadata-Version: 2.1
Name: django-apscheduler
Version: 0.7.0
Summary: APScheduler for Django
Home-page: http://github.com/jcass77/django-apscheduler
Author: Jarek Glowacki, Stas Kaledin, John Cass
Author-email: jarekwg@gmail.com, staskaledin@gmail.com, john.cass77@gmail.com
License: MIT
Keywords: django apscheduler django-apscheduler
Classifier: Development Status :: 4 - Beta
Classifier: Environment :: Web Environment
Classifier: Intended Audience :: Developers
Classifier: License :: OSI Approved :: MIT License
Classifier: Operating System :: OS Independent
Classifier: Programming Language :: Python
Classifier: Programming Language :: Python :: 3
Classifier: Programming Language :: Python :: 3 :: Only
Classifier: Programming Language :: Python :: 3.9
Classifier: Programming Language :: Python :: 3.10
Classifier: Programming Language :: Python :: 3.11
Classifier: Programming Language :: Python :: 3.12
Classifier: Framework :: Django
Classifier: Framework :: Django :: 4.2
Classifier: Framework :: Django :: 5.0
Classifier: Framework :: Django :: 5.1
License-File: LICENSE
License-File: AUTHORS
Requires-Dist: django>=4.2
Requires-Dist: apscheduler<4.0,>=3.2
